wallabag/__init__.py
wallabag/api.py
wallabag/conf.py
wallabag/entry.py
wallabag/wallabag.py
wallabag/wallabag_add.py
wallabag/wallabag_config.py
wallabag/wallabag_delete.py
wallabag/wallabag_help.py
wallabag/wallabag_list.py
wallabag/wallabag_show.py
wallabag/wallabag_update.py
wallabag_cli-0.8.0.dist-info/LICENSE
wallabag_cli-0.8.0.dist-info/METADATA
wallabag_cli-0.8.0.dist-info/WHEEL
wallabag_cli-0.8.0.dist-info/entry_points.txt
wallabag_cli-0.8.0.dist-info/top_level.txt
wallabag_cli-0.8.0.dist-info/RECORD
