Metadata-Version: 2.1
Name: wallabag-cli
Version: 0.8.0
Summary: A command-line client for the self-hosted read-it-later app Wallabag
Home-page: https://github.com/apetresc/wallabag-cli
Author: Michael Scholz
Author-email: UNKNOWN
License: UNKNOWN
Platform: UNKNOWN
Classifier: Programming Language :: Python :: 3
Classifier: License :: OSI Approved :: MIT License
Classifier: Operating System :: OS Independent
Requires-Dist: beautifulsoup4 (>=4.5.1)
Requires-Dist: pycrypto (>=2.6.1)
Requires-Dist: requests (>=2.11.1)
